jdl2makeflow_helpers
