Metadata-Version: 1.2
Name: alien-jdl2makeflow
Version: 0.0.5
Summary: Run AliEn JDLs with Makeflow
Home-page: https://github.com/alisw/release-validation
Author: Matteo Concas and Dario Berzano
Author-email: matteo.concas@cern.ch
License: GPL
Keywords: HEP Computing
Platform: UNKNOWN
Classifier: Development Status :: 4 - Beta
Classifier: Intended Audience :: Education
Classifier: Topic :: Scientific/Engineering :: Physics
Classifier: License :: OSI Approved :: GNU General Public License v3 (GPLv3)
Classifier: Programming Language :: Python :: 2.7
Requires-Python: >=2.7
